LICENSE
MANIFEST.in
README.rst
setup.py
lxc4u/__init__.py
lxc4u/api.py
lxc4u/constants.py
lxc4u/lxc.py
lxc4u/meta.py
lxc4u/overlayutils.py
lxc4u/service.py
lxc4u/utils.py
lxc4u.egg-info/PKG-INFO
lxc4u.egg-info/SOURCES.txt
lxc4u.egg-info/dependency_links.txt
lxc4u.egg-info/not-zip-safe
lxc4u.egg-info/requires.txt
lxc4u.egg-info/top_level.txt